plone.app.multilingual-8.3.2-py3.13-nspkg.pth
plone/app/multilingual/__init__.py
plone/app/multilingual/api.py
plone/app/multilingual/configure.zcml
plone/app/multilingual/events.py
plone/app/multilingual/factory.py
plone/app/multilingual/indexer.py
plone/app/multilingual/interfaces.py
plone/app/multilingual/itg.py
plone/app/multilingual/manager.py
plone/app/multilingual/overrides.zcml
plone/app/multilingual/permissions.py
plone/app/multilingual/permissions.zcml
plone/app/multilingual/setuphandlers.py
plone/app/multilingual/shared_uuid.py
plone/app/multilingual/subscriber.py
plone/app/multilingual/testing.py
plone/app/multilingual/testing.zcml
plone/app/multilingual/upgrades.py
plone/app/multilingual/upgrades.zcml
plone/app/multilingual/browser/__init__.py
plone/app/multilingual/browser/add.py
plone/app/multilingual/browser/configure.zcml
plone/app/multilingual/browser/controlpanel.py
plone/app/multilingual/browser/edit.py
plone/app/multilingual/browser/helper_views.py
plone/app/multilingual/browser/interfaces.py
plone/app/multilingual/browser/menu.py
plone/app/multilingual/browser/migrator.py
plone/app/multilingual/browser/modify.py
plone/app/multilingual/browser/selector.py
plone/app/multilingual/browser/setup.py
plone/app/multilingual/browser/switcher.py
plone/app/multilingual/browser/translate.py
plone/app/multilingual/browser/update.py
plone/app/multilingual/browser/utils.py
plone/app/multilingual/browser/view.py
plone/app/multilingual/browser/viewlets.py
plone/app/multilingual/browser/vocabularies.py
plone/app/multilingual/browser/images/gtranslate.png
plone/app/multilingual/browser/javascript/babel_helper.js
plone/app/multilingual/browser/javascript/jit-yc.js
plone/app/multilingual/browser/javascript/mmap_helper.js
plone/app/multilingual/browser/stylesheet/multilingual.css
plone/app/multilingual/browser/templates/add-form-is-translation.pt
plone/app/multilingual/browser/templates/alternate-languages.pt
plone_app_multilingual-8.3.2.dist-info/METADATA
plone_app_multilingual-8.3.2.dist-info/WHEEL
plone_app_multilingual-8.3.2.dist-info/entry_points.txt
plone_app_multilingual-8.3.2.dist-info/namespace_packages.txt
plone_app_multilingual-8.3.2.dist-info/top_level.txt
plone_app_multilingual-8.3.2.dist-info/RECORD
