Metadata-Version: 2.2
Name: plone.app.multilingual
Version: 8.3.2
Summary: Multilingual Plone Content package
Home-page: https://github.com/plone/plone.app.multilingual
Author: Ramon Navarro, Victor Fernandez de Alba, awello et al
Author-email: r.navarro@iskra.cat
Maintainer: Plone Foundation
Maintainer-email: releasemanager@plone.org
License: GPL
Keywords: language,multilingual,content
Classifier: Development Status :: 5 - Production/Stable
Classifier: Environment :: Web Environment
Classifier: Framework :: Plone
Classifier: Framework :: Plone :: 6.1
Classifier: Framework :: Plone :: 6.2
Classifier: Framework :: Plone :: Core
Classifier: Framework :: Zope :: 5
Classifier: License :: OSI Approved :: GNU General Public License v2 (GPLv2)
Classifier: Operating System :: OS Independent
Classifier: Programming Language :: Python
Classifier: Programming Language :: Python :: 3.10
Classifier: Programming Language :: Python :: 3.11
Classifier: Programming Language :: Python :: 3.12
Classifier: Programming Language :: Python :: 3.13
Requires-Python: >=3.10
Requires-Dist: BTrees
Requires-Dist: plone.app.content
Requires-Dist: plone.app.contentmenu
Requires-Dist: plone.app.dexterity
Requires-Dist: plone.app.event
Requires-Dist: plone.app.i18n
Requires-Dist: plone.app.layout
Requires-Dist: plone.app.querystring
Requires-Dist: plone.app.registry
Requires-Dist: plone.app.uuid
Requires-Dist: plone.app.z3cform
Requires-Dist: plone.autoform
Requires-Dist: plone.base
Requires-Dist: plone.behavior
Requires-Dist: plone.dexterity
Requires-Dist: plone.i18n>=4.0.4
Requires-Dist: plone.indexer
Requires-Dist: plone.locking
Requires-Dist: plone.memoize
Requires-Dist: plone.protect
Requires-Dist: plone.registry
Requires-Dist: plone.schemaeditor
Requires-Dist: plone.supermodel
Requires-Dist: plone.uuid
Requires-Dist: plone.z3cform
Requires-Dist: Products.CMFCore
Requires-Dist: Products.CMFPlone
Requires-Dist: Products.GenericSetup
Requires-Dist: Products.statusmessages
Requires-Dist: setuptools
Requires-Dist: z3c.form
Requires-Dist: z3c.relationfield
Requires-Dist: zc.relation
Requires-Dist: zope.browsermenu
Requires-Dist: zope.intid
Requires-Dist: zope.pagetemplate
Requires-Dist: Zope
Provides-Extra: test
Requires-Dist: plone.app.testing[robot]; extra == "test"
Requires-Dist: plone.app.robotframework; extra == "test"
Requires-Dist: lxml; extra == "test"
Requires-Dist: plone.api; extra == "test"
Requires-Dist: plone.app.contenttypes; extra == "test"
Requires-Dist: plone.app.relationfield; extra == "test"
Requires-Dist: plone.browserlayer; extra == "test"
Requires-Dist: plone.rfc822; extra == "test"
Requires-Dist: plone.testing; extra == "test"
Requires-Dist: robotsuite; extra == "test"
Dynamic: provides-extra
Dynamic: requires-dist
